Sakesama_SpeechToText/main.py
Sakesama2-0.2.dist-info/METADATA
Sakesama2-0.2.dist-info/WHEEL
Sakesama2-0.2.dist-info/top_level.txt
Sakesama2-0.2.dist-info/RECORD
