Metadata-Version: 2.1
Name: Sakesama2
Version: 0.2
Summary: This is a speech to text package created by your Kaijakuri
Author: KaijaKuri
Author-email: example@gmail.com
